tests/__init__.py
tests/test.py
validator/__init__.py
validator/validator.py
darth_validator-1.0.dist-info/LICENSE
darth_validator-1.0.dist-info/METADATA
darth_validator-1.0.dist-info/WHEEL
darth_validator-1.0.dist-info/top_level.txt
darth_validator-1.0.dist-info/RECORD
