Metadata-Version: 2.1
Name: darth-validator
Version: 1.0
Summary: Automatically validates correlation between two workbooks.darth-validator
Home-page: https://github.com/adavila0703/darth-validator
Author: Angel Davila
Author-email: adavila0703@gmail.com
License: UNKNOWN
Platform: UNKNOWN
Classifier: Programming Language :: Python :: 3
Classifier: License :: OSI Approved :: MIT License
Classifier: Operating System :: OS Independent
Requires-Python: >=3.8
